{
  "schema_version": "v1",
  "cert_id": "itpassport_r6",
  "run_id": "dry_run_2026-05-12T13-23-19",
  "stage": 7,
  "page": 112,
  "exported_at": "2026-05-16T14:20:38.067137Z",
  "stage6_verdict": "PASS",
  "leaf_count": 12,
  "entities": [
    {
      "id": "itpassport_r6::term::p112::1",
      "anchor": {
        "page": 112,
        "block_id": "page_112_block_1",
        "section_path": []
      },
      "type": "term",
      "surface": {
        "jp": "内部環境",
        "zh": "内部环境",
        "en": "Internal Environment"
      },
      "definition": {
        "jp": "自社の努力で変えられる項目",
        "zh": "通过本公司努力可以改变的项目",
        "en": "Items that can be changed through the company's own efforts"
      },
      "kana_helper": null
    },
    {
      "id": "itpassport_r6::term::p112::2",
      "anchor": {
        "page": 112,
        "block_id": "page_112_block_2",
        "section_path": []
      },
      "type": "term",
      "surface": {
        "jp": "外部環境",
        "zh": "外部环境",
        "en": "External Environment"
      },
      "definition": {
        "jp": "自社ではコントロールできない項目",
        "zh": "本公司无法控制的项目",
        "en": "Items that the company cannot control"
      },
      "kana_helper": null
    },
    {
      "id": "itpassport_r6::term::p112::3",
      "anchor": {
        "page": 112,
        "block_id": "page_112_block_3",
        "section_path": []
      },
      "type": "term",
      "surface": {
        "jp": "Strengths（強み）",
        "zh": "优势（Strengths）",
        "en": "Strengths"
      },
      "definition": {
        "jp": "内部環境であり、かつ良い影響を及ぼすもの",
        "zh": "属于内部环境且产生良好影响的因素",
        "en": "Internal environment factors that have a positive impact"
      },
      "kana_helper": null
    },
    {
      "id": "itpassport_r6::term::p112::4",
      "anchor": {
        "page": 112,
        "block_id": "page_112_block_4",
        "section_path": []
      },
      "type": "term",
      "surface": {
        "jp": "Weaknesses（弱み）",
        "zh": "劣势（Weaknesses）",
        "en": "Weaknesses"
      },
      "definition": {
        "jp": "内部環境であり、かつ悪い影響を及ぼすもの",
        "zh": "属于内部环境且产生不良影响的因素",
        "en": "Internal environment factors that have a negative impact"
      },
      "kana_helper": null
    },
    {
      "id": "itpassport_r6::term::p112::5",
      "anchor": {
        "page": 112,
        "block_id": "page_112_block_5",
        "section_path": []
      },
      "type": "term",
      "surface": {
        "jp": "Opportunities（機会）",
        "zh": "机会（Opportunities）",
        "en": "Opportunities"
      },
      "definition": {
        "jp": "外部環境であり、かつ良い影響を及ぼすもの",
        "zh": "属于外部环境且产生良好影响的因素",
        "en": "External environment factors that have a positive impact"
      },
      "kana_helper": null
    },
    {
      "id": "itpassport_r6::term::p112::6",
      "anchor": {
        "page": 112,
        "block_id": "page_112_block_6",
        "section_path": []
      },
      "type": "term",
      "surface": {
        "jp": "Threats（脅威）",
        "zh": "威胁（Threats）",
        "en": "Threats"
      },
      "definition": {
        "jp": "外部環境であり、かつ悪い影響を及ぼすもの",
        "zh": "属于外部环境且产生不良影响的因素",
        "en": "External environment factors that have a negative impact"
      },
      "kana_helper": null
    }
  ],
  "polish_items_ref": null
}