{
  "schema_version": "v1",
  "cert_id": "itpassport_r6",
  "run_id": "dry_run_2026-05-12T13-23-19",
  "stage": 7,
  "page": 204,
  "exported_at": "2026-05-16T14:20:38.067137Z",
  "stage6_verdict": "PASS",
  "leaf_count": 20,
  "entities": [
    {
      "id": "itpassport_r6::question::p204::0",
      "anchor": {
        "page": 204,
        "block_id": "page_204_block_0",
        "section_path": []
      },
      "type": "question",
      "stem": {
        "jp": "電子メール、電子掲示板を介したコミュニケーション、情報共有、電子会議などの各種機能を有し、共同作業環境を提供するソフトウェアを何と呼ぶか。 (平成28年度)",
        "zh": "提供电子邮件、电子公告板的通信、信息共享、电子会议等各种功能，并提供协同工作环境的软件称为什么？（平成28年度）",
        "en": "What is the name of software that provides various functions such as communication via email and electronic bulletin boards, information sharing, and electronic conferencing, offering a collaborative work environment? (FY Heisei 28)"
      },
      "choices": [
        {
          "jp": "ア．グループウェア",
          "zh": "A. 群组软件",
          "en": "A. Groupware"
        },
        {
          "jp": "イ．シェアウェア",
          "zh": "B. 共享软件",
          "en": "B. Shareware"
        },
        {
          "jp": "ウ．ファームウェア",
          "zh": "C. 固件",
          "en": "C. Firmware"
        },
        {
          "jp": "エ．フリーウェア",
          "zh": "D. 免费软件",
          "en": "D. Freeware"
        }
      ],
      "answer_index": 0
    },
    {
      "id": "itpassport_r6::question::p204::1",
      "anchor": {
        "page": 204,
        "block_id": "page_204_block_1",
        "section_path": []
      },
      "type": "question",
      "stem": {
        "jp": "SaaSを説明したものはどれか。 (平成21年度)",
        "zh": "以下哪一项是对软件即服务（SaaS）的说明？（平成21年度）",
        "en": "Which of the following describes SaaS (Software as a Service)? (FY Heisei 21)"
      },
      "choices": [
        {
          "jp": "ア．コンピュータ設備の利用をサービスとして提供し、使用料を課金する。",
          "zh": "A. 以服务的形式提供计算机设备的使用，并按使用费收费。",
          "en": "A. Provides the use of computer equipment as a service and charges usage fees."
        },
        {
          "jp": "イ．情報システム部門の機能の一部を受託し、業務委託料を課金する。",
          "zh": "B. 承接信息系统部门的部分职能，并收取业务委托费。",
          "en": "B. Takes on part of the functions of the information systems department and charges business outsourcing fees."
        },
        {
          "jp": "ウ．ソフトウェアの機能を複数の企業にインターネット経由でサービスとして提供し、使用料を課金する。",
          "zh": "C. 通过互联网将软件功能作为服务提供给多家企业，并收取使用费。",
          "en": "C. Provide software functions as a service to multiple companies via the Internet and charge usage fees."
        },
        {
          "jp": "エ．ソフトウェアをダウンロードさせる対価としてライセンス料を課金する。",
          "zh": "D. 以允许下载软件为对价收取许可费。",
          "en": "D. Charge license fees in exchange for allowing software downloads."
        }
      ],
      "answer_index": 2
    },
    {
      "id": "itpassport_r6::question::p204::2",
      "anchor": {
        "page": 204,
        "block_id": "page_204_block_2",
        "section_path": []
      },
      "type": "question",
      "stem": {
        "jp": "自然災害などによるシステム障害に備えるため、自社のコンピュータセンタとは別の地域に自社のバックアップサーバを設置したい。このとき利用する外部業者のサービスとして、適切なものはどれか。 (平成28年度)",
        "zh": "为了应对自然灾害等导致的系统故障，希望在与本公司计算机中心不同的地区设置本公司的备份服务器。此时利用的外部业者服务，恰当的是哪一项？（平成28年度）",
        "en": "To prepare for system failures caused by natural disasters, you want to install your company's backup server in a region different from your own computer center. Which external vendor service is appropriate to use in this case? (FY Heisei 28)"
      },
      "choices": [
        {
          "jp": "ア．ASP",
          "zh": "A. 应用服务提供商（ASP）",
          "en": "A. ASP (Application Service Provider)"
        },
        {
          "jp": "イ．BPO",
          "zh": "B. 业务流程外包（BPO）",
          "en": "B. BPO (Business Process Outsourcing)"
        },
        {
          "jp": "ウ．SaaS",
          "zh": "C. 软件即服务（SaaS）",
          "en": "C. SaaS (Software as a Service)"
        },
        {
          "jp": "エ．ハウジング",
          "zh": "D. 主机托管服务",
          "en": "D. Housing Service"
        }
      ],
      "answer_index": 3
    },
    {
      "id": "itpassport_r6::question::p204::3",
      "anchor": {
        "page": 204,
        "block_id": "page_204_block_3",
        "section_path": []
      },
      "type": "question",
      "stem": {
        "jp": "RPA (Robotic Process Automation) に関する記述として、最も適切なものはどれか。 (平成31年度)",
        "zh": "关于机器人流程自动化（RPA）的描述，最恰当的是哪一项？（平成31年度）",
        "en": "Which of the following is the most appropriate description regarding RPA (Robotic Process Automation)? (FY Heisei 31)"
      },
      "choices": [
        {
          "jp": "ア．ホワイトカラーの定型的な事務作業を、ソフトウェアで実現されたロボットに代替させることによって、自動化や効率化を図る。",
          "zh": "A. 通过用软件实现的机器人替代白领的常规事务工作，从而实现自动化与效率化。",
          "en": "A. Replace white-collar routine clerical work with software-based robots to achieve automation and efficiency."
        },
        {
          "jp": "イ．システムの利用者が、主体的にシステム管理や運用を行うことによって、利用者のITリテラシーの向上や、システムベンダーへの依存の軽減などを実現する。",
          "zh": "B. 由系统的用户主动进行系统管理和运维，以此提升用户的IT素养并减少对系统供应商的依赖。",
          "en": "B. System users proactively perform system management and operation, thereby improving users' IT literacy and reducing dependence on system vendors."
        },
        {
          "jp": "ウ．組立てや搬送などにハードウェアのロボットを用いることによって、工場の生産活動の自動化を実現する。",
          "zh": "C. 通过在装配和搬运等环节使用硬件机器人，实现工厂生产活动的自动化。",
          "en": "C. Use hardware robots for assembly, transportation, and similar tasks to achieve automation of factory production activities."
        },
        {
          "jp": "エ．企業の一部の業務を外部の組織に委託することによって、自社のリソースを重要な領域に集中したり、コストの最適化や業務の高効率化などを実現したりする。",
          "zh": "D. 通过将企业的部分业务委托给外部组织，将自身资源集中于重要领域，并实现成本优化和业务高效化等目标。",
          "en": "D. Outsource part of a company's operations to external organizations to concentrate internal resources on key areas and achieve cost optimization and operational efficiency."
        }
      ],
      "answer_index": 0
    }
  ],
  "polish_items_ref": null
}