{
  "schema_version": "v1",
  "cert_id": "itpassport_r6",
  "run_id": "dry_run_2026-05-12T13-23-19",
  "stage": 7,
  "page": 493,
  "exported_at": "2026-05-16T14:20:38.067137Z",
  "stage6_verdict": "PASS",
  "leaf_count": 13,
  "entities": [
    {
      "id": "itpassport_r6::term::p493::0",
      "anchor": {
        "page": 493,
        "block_id": "page_493_block_0",
        "section_path": []
      },
      "type": "term",
      "surface": {
        "jp": "グローバルIPアドレス",
        "zh": "公网IP地址",
        "en": "Global IP Address"
      },
      "definition": {
        "jp": "インターネットに接続するコンピュータに割り当てられる、世界で唯一(一意)のIPアドレス",
        "zh": "分配给连接到互联网的计算机的、全球唯一的IP地址",
        "en": "A globally unique IP address assigned to computers connected to the Internet"
      },
      "kana_helper": null
    },
    {
      "id": "itpassport_r6::term::p493::1",
      "anchor": {
        "page": 493,
        "block_id": "page_493_block_1",
        "section_path": []
      },
      "type": "term",
      "surface": {
        "jp": "プライベートIPアドレス",
        "zh": "私有IP地址",
        "en": "Private IP Address"
      },
      "definition": {
        "jp": "インターネットに直接は接続しないコンピュータに割り当てられる、LAN内だけで扱うIPアドレス",
        "zh": "分配给不直接连接互联网的计算机、仅在LAN内使用的IP地址",
        "en": "An IP address assigned to computers not directly connected to the Internet, used only within a LAN"
      },
      "kana_helper": null
    },
    {
      "id": "itpassport_r6::term::p493::2",
      "anchor": {
        "page": 493,
        "block_id": "page_493_block_2",
        "section_path": []
      },
      "type": "term",
      "surface": {
        "jp": "NAT(Network Address Translation)",
        "zh": "网络地址转换（NAT）",
        "en": "NAT (Network Address Translation)"
      },
      "definition": {
        "jp": "プライベートIPアドレスをグローバルIPアドレスへ変換する技術",
        "zh": "将私有IP地址转换为公网IP地址的技术",
        "en": "Technology that converts private IP addresses into global IP addresses"
      },
      "kana_helper": null
    },
    {
      "id": "itpassport_r6::table::p493::3",
      "anchor": {
        "page": 493,
        "block_id": "page_493_block_3",
        "section_path": []
      },
      "type": "table",
      "caption": {
        "jp": "IPアドレスの種類",
        "zh": "IP地址的种类",
        "en": "Types of IP Address"
      },
      "rows": [
        [
          {
            "jp": "種類",
            "zh": "种类",
            "en": "Type"
          },
          {
            "jp": "説明",
            "zh": "说明",
            "en": "Description"
          }
        ],
        [
          {
            "jp": "グローバルIPアドレス",
            "zh": "公网IP地址",
            "en": "Global IP Address"
          },
          {
            "jp": "インターネットに接続するコンピュータに割り当てられる、世界で唯一(一意)のIPアドレス",
            "zh": "分配给连接到互联网的计算机的、全球唯一的IP地址",
            "en": "A globally unique IP address assigned to computers connected to the Internet"
          }
        ],
        [
          {
            "jp": "プライベートIPアドレス",
            "zh": "私有IP地址",
            "en": "Private IP Address"
          },
          {
            "jp": "インターネットに直接は接続しないコンピュータに割り当てられる、LAN内だけで扱うIPアドレス",
            "zh": "分配给不直接连接互联网的计算机、仅在LAN内使用的IP地址",
            "en": "An IP address assigned to computers not directly connected to the Internet, used only within a LAN"
          }
        ]
      ]
    }
  ],
  "polish_items_ref": null
}